{
  "files": {
    "total": {
      "withPatternfly": {
        "js": 23,
        "scss": 13
      },
      "js": 61,
      "scss": 15
    },
    "withPatternfly": {
      "js": {
        "files": [
          "/src/components/ActionsResolvedCard.js",
          "/src/components/Alerts/ExecuteBanner.js",
          "/src/components/Alerts/UpsellBanner.js",
          "/src/components/ConfirmationDialog.js",
          "/src/components/CreatePlanModal/ModalSteps/PlanName.js",
          "/src/components/CreatePlanModal/ModalSteps/PlanSystems.js",
          "/src/components/DeleteButton.js",
          "/src/components/Dialogs/TextInputDialog.js",
          "/src/components/ExecuteButton.js",
          "/src/components/NewRemediationButton.js",
          "/src/components/RemediationDetailsDropdown.js",
          "/src/components/RemediationDetailsSystemDropdown.js",
          "/src/components/RemediationDetailsTable.js",
          "/src/components/RemediationTable.js",
          "/src/components/ResolutionModal/ResolutionStep.js",
          "/src/components/ResolutionStatusIcon.js",
          "/src/components/SystemForActionButton.js",
          "/src/components/TestButtons.js",
          "/src/components/ToolbarActionsDropdown.js",
          "/src/Routes.js",
          "/src/routes/RemediationDetails.js",
          "/src/skeletons/SkeletonTable.js",
          "/src/Utilities/model.js"
        ]
      },
      "scss": {
        "files": [
          "/src/App.scss",
          "/src/components/CreatePlanModal/ModalSteps/PlanSystems.scss",
          "/src/components/DeleteButton.scss",
          "/src/components/ExecuteButton.scss",
          "/src/components/Layouts/DescriptionList.scss",
          "/src/components/RemediationDetailsTable.scss",
          "/src/components/RemediationTable.scss",
          "/src/components/ResolutionModal/ChooseResolutionModal.scss",
          "/src/components/ResolutionStatusIcon.scss",
          "/src/components/ToolbarActionsDropdown.scss",
          "/src/routes/Home.scss",
          "/src/routes/RemediationDetails.scss",
          "/src/skeletons/RemediationDetailsSkeleton.scss"
        ]
      }
    }
  },
  "imports": {
    "@patternfly/react-core": {
      "Card": 2,
      "CardHeader": 2,
      "CardBody": 2,
      "Progress": 1,
      "ProgressMeasureLocation": 1,
      "Alert": 3,
      "AlertActionLink": 1,
      "AlertActionCloseButton": 1,
      "Stack": 3,
      "StackItem": 3,
      "Button": 12,
      "Modal": 4,
      "Form": 3,
      "FormGroup": 3,
      "TextInput": 2,
      "Radio": 2,
      "Select": 1,
      "SelectOption": 1,
      "TextContent": 1,
      "Text": 1,
      "TextVariants": 1,
      "Dropdown": 4,
      "DropdownPosition": 2,
      "KebabToggle": 4,
      "Pagination": 2,
      "ToolbarItem": 2,
      "ToolbarGroup": 2,
      "Bullseye": 1,
      "EmptyState": 1,
      "EmptyStateIcon": 1,
      "EmptyStateBody": 1,
      "Title": 1,
      "Label": 1,
      "Split": 3,
      "SplitItem": 3,
      "*": 1,
      "Level": 1,
      "LevelItem": 1,
      "Breadcrumb": 1,
      "BreadcrumbItem": 1,
      "Flex": 1,
      "FlexItem": 1,
      "FlexModifiers": 1,
      "Tooltip": 1
    },
    "@patternfly/react-table": {
      "TableHeader": 4,
      "Table": 4,
      "TableBody": 3,
      "TableVariant": 4,
      "sortable": 2,
      "*": 1
    },
    "@patternfly/react-icons": {
      "CheckCircleIcon": 3,
      "ExclamationCircleIcon": 2,
      "WrenchIcon": 1,
      "QuestionCircleIcon": 1,
      "*": 1
    }
  },
  "classes": {
    "pf-l-page__main": 1,
    "pf-c-page__main": 1,
    "pf-c-form__helper-text.pf-m-error": 1,
    "pf-c-form__group": 1,
    "pf-c-button.pf-m-link.ins-c-button__danger-link": 1,
    "pf-c-progress.remediationProgress{": 1,
    "pf-c-progress__bar": 1,
    "pf-c-table__expandable-row-content": 1,
    "pf-c-card__body": 1,
    "pf-c-check": 1,
    "pf-c-label": 1,
    "pf-c-dropdown__menu": 1,
    "pf-l-page-header": 1,
    "pf-c-content": 1,
    "pf-c-page-header.pf-c-page__main-section": 1,
    "pf-c-modal-box__body{": 1,
    "pf-c-card{": 1,
    "pf-c-card__header": 2,
    "pf-c-card__header.ins-m-card__header-bold": 1,
    "pf-c-progress__measure": 1,
    "pf-l-grid": 1,
    "pf-l-stack,": 1,
    "pf-l-stack__item": 2,
    "pf-l-stack__item:not(.ins-m-border-top){": 1,
    "pf-c-breadcrumb__item": 1
  },
  "scssVars": {
    "--pf-global--danger-color-": 3,
    "--pf-c-button--m": 9,
    "--pf-global--spacer--xs": 1,
    "--pf-chart-global--danger": 1,
    "--pf-global--FontSize--md": 2,
    "--pf-global--FontSize--lg": 1,
    "--pf-global--FontWeight--redhatfont": 1,
    "--pf-global--success-color-": 3,
    "--pf-c-progress--GridGap": 1,
    "--pf-global--Color--200": 1,
    "--pf-global--spacer--lg": 1,
    "--pf-global--spacer--sm": 1
  },
  "repo": "https://github.com/RedHatInsights/insights-remediations-frontend",
  "name": "Insights-Remediations",
  "date": "2020-02-19T17:38:24.544Z"
}