{
  "files": {
    "total": {
      "withPatternfly": {},
      "js": 41,
      "scss": 6
    },
    "withPatternfly": {}
  },
  "imports": {},
  "classes": {},
  "cssVars": {},
  "repo": "https://github.com/theforeman/foreman-js",
  "name": "Foreman-Tools",
  "date": "2024-07-22T14:47:45.240Z",
  "dependencies": {
    "@apollo/react-testing": 1,
    "@babel/core": 3,
    "@babel/plugin-proposal-class-properties": 1,
    "@babel/plugin-proposal-object-rest-spread": 1,
    "@babel/plugin-syntax-dynamic-import": 1,
    "@babel/plugin-transform-modules-amd": 1,
    "@babel/plugin-transform-modules-commonjs": 1,
    "@babel/plugin-transform-modules-systemjs": 1,
    "@babel/plugin-transform-object-assign": 1,
    "@babel/preset-env": 2,
    "@babel/preset-react": 1,
    "@commitlint/cli": 1,
    "@commitlint/config-conventional": 1,
    "@testing-library/jest-dom": 1,
    "@testing-library/react": 1,
    "@testing-library/react-hooks": 1,
    "@theforeman/builder": 1,
    "@theforeman/find-foreman": 1,
    "@theforeman/vendor-core": 3,
    "@theforeman/vendor-dev": 1,
    "axios-mock-adapter": 1,
    "babel-eslint": 1,
    "babel-jest": 1,
    "babel-loader": 1,
    "babel-plugin-dynamic-import-node": 2,
    "babel-plugin-module-resolver": 1,
    "chalk": 1,
    "cheerio": 1,
    "commander": 3,
    "commitlint-config-cz": 1,
    "compression-webpack-plugin": 1,
    "copy-webpack-plugin": 1,
    "coveralls": 1,
    "css-loader": 1,
    "cz-customizable": 1,
    "enzyme": 1,
    "enzyme-adapter-react-16": 1,
    "enzyme-to-json": 1,
    "eslint": 3,
    "eslint-import-resolver-alias": 1,
    "eslint-plugin-jquery": 1,
    "eslint-plugin-patternfly-react": 2,
    "eslint-plugin-promise": 1,
    "eslint-plugin-react-hooks": 1,
    "file-loader": 1,
    "identity-obj-proxy": 1,
    "jest": 1,
    "jest-prop-type-error": 1,
    "jest-transform-graphql": 1,
    "jsx-ast-utils": 1,
    "lerna": 1,
    "lodash": 1,
    "mini-css-extract-plugin": 1,
    "patternflyVersions": {
      "eslint-plugin-patternfly-react": [
        "^4.1.8",
        "0.2.0"
      ]
    },
    "prettier": 1,
    "raf": 1,
    "react-redux-test-utils": 1,
    "react-test-renderer": 1,
    "rimraf": 2,
    "sass": 1,
    "sass-loader": 1,
    "scss-bundle": 1,
    "surge": 1,
    "url-loader": 1,
    "webpack": 1,
    "webpack-bundle-analyzer": 1,
    "webpack-cli": 1,
    "webpack-inject-plugin": 1,
    "webpack-stats-plugin": 1
  }
}